pm4py_wrapper/cli.py
pm4py_wrapper/wrapper.py
pm4py_wrapper-1.3.1.dist-info/entry_points.txt
pm4py_wrapper-1.3.1.dist-info/LICENSE
pm4py_wrapper-1.3.1.dist-info/WHEEL
pm4py_wrapper-1.3.1.dist-info/METADATA
pm4py_wrapper-1.3.1.dist-info/RECORD
